setup.py
douban_client/__init__.py
douban_client/client.py
douban_client/scope.py
douban_client.egg-info/PKG-INFO
douban_client.egg-info/SOURCES.txt
douban_client.egg-info/dependency_links.txt
douban_client.egg-info/requires.txt
douban_client.egg-info/top_level.txt
douban_client/api/__init__.py
douban_client/api/album.py
douban_client/api/base.py
douban_client/api/book.py
douban_client/api/comment.py
douban_client/api/discussion.py
douban_client/api/doumail.py
douban_client/api/error.py
douban_client/api/event.py
douban_client/api/guess.py
douban_client/api/miniblog.py
douban_client/api/movie.py
douban_client/api/music.py
douban_client/api/note.py
douban_client/api/online.py
douban_client/api/photo.py
douban_client/api/review.py
douban_client/api/subject.py
douban_client/api/user.py
tests/__init__.py
tests/framework.py
tests/local_config.py
tests/run.py
tests/test_api_album.py
tests/test_api_book.py
tests/test_api_bubbler.py
tests/test_api_discussion.py
tests/test_api_doumail.py
tests/test_api_error.py
tests/test_api_event.py
tests/test_api_guess.py
tests/test_api_miniblog.py
tests/test_api_movie.py
tests/test_api_music.py
tests/test_api_note.py
tests/test_api_oauth2.py
tests/test_api_online.py
tests/test_api_photo.py
tests/test_api_user.py